bee_util/__init__.py
bee_util/gevent.py
bee_util/thread.py
bee_util/data/__init__.py
bee_util/data/const.py
bee_util/data/map.py
bee_util/data/option.py
bee_util/data/pool.py
bee_util/data/guid/__init__.py
bee_util/data/guid/base32hex.py
bee_util/data/guid/guid.py
bee_util/debug/__init__.py
bee_util/debug/stack.py
bee_util/errors/__init__.py
bee_util/errors/error.py
bee_util/ext/__init__.py
bee_util/ext/files.py
bee_util/i18n/__init__.py
bee_util/i18n/_i18n.py
py_bee_util-0.1.2.dist-info/LICENSE.rst
py_bee_util-0.1.2.dist-info/METADATA
py_bee_util-0.1.2.dist-info/WHEEL
py_bee_util-0.1.2.dist-info/top_level.txt
py_bee_util-0.1.2.dist-info/RECORD
