Metadata-Version: 2.1
Name: py-bee-util
Version: 0.1.2
Summary: Bee is an all-in-one python framework for simplifying micro service program development.
Home-page: https://github.com/py-bee/bee-util
Author: wenchao.hao
Author-email: awenhaowenchao@hotmail.com
License: MIT
Platform: UNKNOWN
Classifier: License :: OSI Approved :: MIT License
Classifier: Programming Language :: Python
Classifier: Programming Language :: Python :: 3
Classifier: Programming Language :: Python :: 3.6
Classifier: Programming Language :: Python :: Implementation :: CPython
Classifier: Programming Language :: Python :: Implementation :: PyPy
Requires-Python: >=3.6.0
Requires-Dist: gevent (==1.4.0)
Requires-Dist: greenlet (==1.0.0)
Requires-Dist: typing-extensions (==3.7.4.3)
Requires-Dist: pyyaml (>=5.4.1)
